configuration/configuration.testing.py
netbox_dhcp/__init__.py
netbox_dhcp/apps.py
netbox_dhcp/navigation.py
netbox_dhcp/template_content.py
netbox_dhcp/urls.py
netbox_dhcp/api/nested_serializers.py
netbox_dhcp/api/serializers.py
netbox_dhcp/api/urls.py
netbox_dhcp/api/views.py
netbox_dhcp/api/serializers_/client_class.py
netbox_dhcp/api/serializers_/dhcp_cluster.py
netbox_dhcp/api/serializers_/dhcp_server.py
netbox_dhcp/api/serializers_/host_reservation.py
netbox_dhcp/api/serializers_/mixins.py
netbox_dhcp/api/serializers_/option.py
netbox_dhcp/api/serializers_/option_definition.py
netbox_dhcp/api/serializers_/pd_pool.py
netbox_dhcp/api/serializers_/pool.py
netbox_dhcp/api/serializers_/shared_network.py
netbox_dhcp/api/serializers_/subnet.py
netbox_dhcp/choices/__init__.py
netbox_dhcp/choices/ddns.py
netbox_dhcp/choices/dhcp_cluster.py
netbox_dhcp/choices/dhcp_server.py
netbox_dhcp/choices/host_reservation.py
netbox_dhcp/choices/netbox_dhcp.py
netbox_dhcp/choices/option.py
netbox_dhcp/fields/__init__.py
netbox_dhcp/fields/choice_array.py
netbox_dhcp/filtersets/__init__.py
netbox_dhcp/filtersets/client_class.py
netbox_dhcp/filtersets/dhcp_cluster.py
netbox_dhcp/filtersets/dhcp_server.py
netbox_dhcp/filtersets/host_reservation.py
netbox_dhcp/filtersets/mixins.py
netbox_dhcp/filtersets/option.py
netbox_dhcp/filtersets/option_definition.py
netbox_dhcp/filtersets/pd_pool.py
netbox_dhcp/filtersets/pool.py
netbox_dhcp/filtersets/shared_network.py
netbox_dhcp/filtersets/subnet.py
netbox_dhcp/forms/__init__.py
netbox_dhcp/forms/client_class.py
netbox_dhcp/forms/dhcp_cluster.py
netbox_dhcp/forms/dhcp_server.py
netbox_dhcp/forms/host_reservation.py
netbox_dhcp/forms/option.py
netbox_dhcp/forms/option_definition.py
netbox_dhcp/forms/pd_pool.py
netbox_dhcp/forms/pool.py
netbox_dhcp/forms/shared_network.py
netbox_dhcp/forms/subnet.py
netbox_dhcp/forms/mixins/__init__.py
netbox_dhcp/forms/mixins/bulk_edit.py
netbox_dhcp/forms/mixins/bulk_import.py
netbox_plugin_dhcp-0.1.3.dist-info/licenses/LICENSE
netbox_plugin_dhcp-0.1.3.dist-info/METADATA
netbox_plugin_dhcp-0.1.3.dist-info/WHEEL
netbox_plugin_dhcp-0.1.3.dist-info/top_level.txt
netbox_plugin_dhcp-0.1.3.dist-info/RECORD
