Metadata-Version: 2.4
Name: netbox-plugin-dhcp
Version: 0.1.3
Summary: NetBox DHCP is a NetBox plugin for DHCP data.
Author-email: Peter Eckel <pe@sys4.de>
Project-URL: Homepage, https://github.com/sys4/netbox-plugin-dhcp
Project-URL: Repository, https://github.com/sys4/netbox-plugin-dhcp
Project-URL: Issues, https://github.com/sys4/netbox-plugin-dhcp/issues
Keywords: netbox,netbox-plugin,dhcp
Classifier: Development Status :: 4 - Beta
Requires-Python: >=3.12
License-File: LICENSE
Dynamic: license-file
